djresttoolkit/__init__.py
djresttoolkit/admin.py
djresttoolkit/apps.py
djresttoolkit/py.typed
djresttoolkit/cache/__init__.py
djresttoolkit/cache/mixins/__init__.py
djresttoolkit/cache/mixins/_cache_action_mixin.py
djresttoolkit/cache/mixins/_cache_invalidate_mixin.py
djresttoolkit/cache/mixins/_cache_key_mixin.py
djresttoolkit/cache/mixins/_cache_list_retrieve_mixin.py
djresttoolkit/cache/mixins/_cache_ops_mixin.py
djresttoolkit/dbseed/__init__.py
djresttoolkit/dbseed/models/__init__.py
djresttoolkit/dbseed/models/_choice_field.py
djresttoolkit/dbseed/models/_gen.py
djresttoolkit/dbseed/models/_seed_model.py
djresttoolkit/envconfig/__init__.py
djresttoolkit/envconfig/_base_env_config.py
djresttoolkit/mail/__init__.py
djresttoolkit/mail/_email_sender.py
djresttoolkit/mail/_models.py
djresttoolkit/mail/_types.py
djresttoolkit/management/__init__.py
djresttoolkit/management/commands/__init__.py
djresttoolkit/management/commands/dbflush.py
djresttoolkit/management/commands/dbseed.py
djresttoolkit/middlewares/__init__.py
djresttoolkit/middlewares/_response_time_middleware.py
djresttoolkit/migrations/__init__.py
djresttoolkit/models/__init__.py
djresttoolkit/models/mixins/__init__.py
djresttoolkit/models/mixins/_model_choice_fields_mixin.py
djresttoolkit/pagination/__init__.py
djresttoolkit/pagination/_page_number_pagination.py
djresttoolkit/pagination/_paginated_data_builder.py
djresttoolkit/renderers/__init__.py
djresttoolkit/renderers/_throttle_info_json_renderer.py
djresttoolkit/serializers/__init__.py
djresttoolkit/serializers/_enhanced_model_serializer.py
djresttoolkit/serializers/mixins/__init__.py
djresttoolkit/serializers/mixins/_absolute_url_file_mixin.py
djresttoolkit/serializers/mixins/_bulk_create_mixin.py
djresttoolkit/throttling/__init__.py
djresttoolkit/throttling/_throttle_inspector.py
djresttoolkit/urls/__init__.py
djresttoolkit/urls/_build_absolute_uri.py
djresttoolkit/views/__init__.py
djresttoolkit/views/_apiviews/__init__.py
djresttoolkit-1.2.1.dist-info/METADATA
djresttoolkit-1.2.1.dist-info/WHEEL
djresttoolkit-1.2.1.dist-info/entry_points.txt
djresttoolkit-1.2.1.dist-info/licenses/LICENSE
djresttoolkit-1.2.1.dist-info/RECORD
