Metadata-Version: 2.4
Name: djresttoolkit
Version: 1.2.1
Summary: A collection of Django and DRF utilities to simplify API development.
Project-URL: Homepage, https://github.com/shaileshpandit141/djresttoolkit
Project-URL: Documentation, https://shaileshpandit141.github.io/djresttoolkit
Project-URL: Source, https://github.com/shaileshpandit141/djresttoolkit
Project-URL: Issues, https://github.com/shaileshpandit141/djresttoolkit/issues
Project-URL: License, https://github.com/shaileshpandit141/djresttoolkit/blob/main/LICENSE
Author-email: shaileshpandit141 <shaileshpandit141@gmail.com>
License: # MIT License
License-File: LICENSE
Keywords: api-development,django,django-authentication,django-email,django-helpers,django-mixins,django-pagination,django-rest,django-rest-framework-utilities,django-rest-utilities,django-serializers,django-shortcuts,django-utilities,djangorestframework,drf,python-package,rest-api
Classifier: Development Status :: 4 - Beta
Classifier: Framework :: Django
Classifier: Framework :: Django :: 4.0
Classifier: Intended Audience :: Developers
Classifier: License :: OSI Approved :: MIT License
Classifier: Programming Language :: Python :: 3.10
Classifier: Programming Language :: Python :: 3.11
Classifier: Programming Language :: Python :: 3.12
Classifier: Programming Language :: Python :: 3.13
Classifier: Topic :: Software Development :: Libraries
Classifier: Topic :: Utilities
Classifier: Typing :: Typed
Requires-Python: >=3.13
Requires-Dist: faker>=37.5.3
Requires-Dist: pydantic>=2.11.7
Provides-Extra: dev
Requires-Dist: mypy; extra == 'dev'
Requires-Dist: pytest; extra == 'dev'
Requires-Dist: ruff; extra == 'dev'
